[
  {
    "id": "853cc7c0-f1a4-4b79-ba12-e7f9b2e0946c",
    "name": "Kristine Wyman",
    "phone": "1-945-558-0989 x83708",
    "email": "Darlene61@yahoo.com",
    "job": "District Program Designer"
  },
  {
    "id": "586976da-7b77-42ea-b0dc-24c477eaad66",
    "name": "Heidi Wunsch-Effertz",
    "phone": "(529) 246-2744",
    "email": "Dan86@yahoo.com",
    "job": "Global Security Producer"
  },
  {
    "id": "b327aed7-b8bf-4c36-873d-da582be5eabc",
    "name": "Delbert Mosciski",
    "phone": "1-282-488-7290",
    "email": "Adolph.Leannon@gmail.com",
    "job": "Legacy Creative Strategist"
  },
  {
    "id": "bb09ce55-15c4-431c-b293-f730cc2e0c56",
    "name": "Jonathon Bailey",
    "phone": "447.362.3460 x40624",
    "email": "Saige56@gmail.com",
    "job": "Senior Solutions Analyst"
  },
  {
    "id": "04068c01-ee9a-4bc6-b7de-6f64f6dbd92a",
    "name": "Rene Zboncak",
    "phone": "659.485.2605 x7610",
    "email": "Mattie_Jast18@yahoo.com",
    "job": "Investor Usability Facilitator"
  }
]